{
    "1": {
        "type": "st",
        "storey": [
            0.0,
            3.7,
            7.4,
            11.1,
            14.8,
            18.5
        ],
        "location": [
            [
                -5.0,
                -44.2875
            ],
            [
                64.0632,
                -44.2875
            ]
        ],
        "ids": [
            "2zidDkqJYVGvzkW_KoG13A",
            "3XRokkaah3JuG3PDEJB0nD",
            "3WXmw7wpUiHgvyNPywVTA6",
            "1_BB$DGGRqHBmePdDY9bu7",
            "1Oi$53EKdjIuLA8FER84OK",
            "1kN6oxnBynJfNWpF35LP38",
            "0wummMVeJRIBFnbcVn9niQ",
            "1QGRFNtXipHhCcklcGmzrg",
            "3ysneAwFJ$GeX7m8Nq250o",
            "0RL$J9lksEJw9cKWOK7Aon",
            "3IFvk43xz2HgrJ1m7X$SQn",
            "08R97XM1L5HP_4qLB5LycH",
            "0tn5O72YW8I8zoFGFPAnJR",
            "1FhlZu4A7EHfxGtmstRKmN"
        ],
        "neighbor": {
            "0.0": {
                "8": -4.425000000000004,
                "18": 3.4125000000000014
            },
            "3.7": {
                "8": -4.425000000000004,
                "18": 3.4125000000000014
            },
            "7.4": {
                "8": -4.425000000000004,
                "18": 3.4125000000000014
            },
            "11.1": {
                "8": -4.425000000000004,
                "18": 3.4125000000000014
            },
            "14.8": {
                "8": -4.425000000000004,
                "18": 3.4125000000000014
            }
        }
    },
    "2": {
        "type": "st",
        "storey": [
            0.0,
            3.7,
            7.4,
            11.1,
            14.8
        ],
        "location": [
            [
                5.4375,
                -68.0
            ],
            [
                5.4375,
                5.0894
            ]
        ],
        "ids": [
            "07_7DFRQeqHv0g_qcRauhP",
            "08z9HKUu1nHgMKbRraK634",
            "0BBQ1$QU$LIPfDOPGWry7i",
            "0HAt$lXehIHwN0SvWm0ngE",
            "0JTDpJ4GvAJAOAQtxyHb7L",
            "0SKRYfiMEXHALT9EiXDhva",
            "0TXaJ1dse1JRGddLJKBFK_",
            "0Ta6qpkfo3Ggiuhjaf_7pO",
            "0TsperTeZuIBvDfv6FbNvZ",
            "0VGlCokFK5I9n_1G8k9bXZ",
            "0Yeyt0vfNZJeCjxe7ZeBji",
            "0Yv9XnTkZtJuXeiS6Dq1g5",
            "0a3El7qHajIfHW9EqzPdEx",
            "0ix9UR5e2JIfb4UCv6EUpN",
            "0uohCJbu1FHAt17rWTxVlI",
            "0viRfa46HhH9CEBI8OzoNE",
            "17$FrioAORJwKlxTF0SWfr",
            "19p8Zqh8dlJe4nEwh1DU6y",
            "1CJEA3lECwGvRfAmfS8pa7",
            "1CcZM3lT8WJvrCSDZsHtwX",
            "1FTsIyaj71JBc7wQoH90LG",
            "1HPhA11vXeJ8w0Ur0$VpD3",
            "1OEmy29VgSJPNgSPINNhR6",
            "1OdGGtsj6UJf$eoVXHLACb",
            "1_MKcxXloyIRBgJvYHibAJ",
            "1v9JMjQfrfJB6YScaL4c_U",
            "1xV8mNnX9nJONHAc76F96u",
            "2EIWibJv7vHfF_l8R_fhIH",
            "2aePSZyHfsIOaSfhX4WnHU",
            "2csT6EsogYJfwAXvSQ4Qlc",
            "2t5$vlwXEUHAcn45U0lSAn",
            "2wnh8WudaXJBrJrtD4ni8R",
            "2xn$VLT0kcGgRKjymrOdgP",
            "2yndS87WewIh5O8onJDqK8",
            "2ywuw_oLkjJwx2BE4TljYd",
            "35_otWIiZDJgc7ZLKNJTlM",
            "36JDKM3zU3IPTgscbqVJwS",
            "3CydeM2GpLGQMLTCr2KpQT",
            "3QKbCBt6vGI9ISyzURnf2q",
            "3TJADEFfQuGOn64lCLEMIb",
            "3bPiOjE_2KIx9Wdr4Gsz3E",
            "3gQIO1hH1OJRnhdS$HCPWj",
            "3paTauFHLbHh5oJk3xwcEj",
            "3rEkJQWqvpHOh9T7lyy_Dw",
            "3rOIr6QUTzGxLtgpQ3rTTR",
            "3s_BlWNm0HJ9A7fD5tJx6I",
            "3zSEoz5S3TIPhS8pxxPuXi",
            "0sHwxQJDrfJ8AxiTo9d6Ho",
            "1uovkV$hLLJR3ovVz1xAP1",
            "07ACARLGp$Hw0FnTxCI10f",
            "3H9jmGsi8vJhbTt9ASLpeY",
            "3hVbYbsu1FHuJD9CY$_XFp",
            "3k$yhxn4gfJQbLScCuU2EO",
            "0cxUxyqWTHGA9W$QThw0nC",
            "0nPjJVeiPzJBQMGHEv5fGq",
            "0WOx4F9i4mHPL$orJc9SxH",
            "1hBiLgThHNH8yZkM$L3pzK",
            "1Vv8IAODI2IhmnXljAi2hf",
            "28DpRJABfPHhFG7YbX0Lju",
            "3W6xCGLVxGJ9sBrAeOVFrR",
            "2G8obHe4fJGeiO9Rf7ECI8",
            "3XUkhpFZqCJveqBbLOHBzQ",
            "1Pa3aotg3nGBbY2FGmmPtA",
            "2qdos6UyHOHg$8f4Tng9b8",
            "3EQLlptFDVJhWiUtCqak7V",
            "27YRnGZcmpJuWaMqJRubNx",
            "3mU2hzAIg4JxjBgLK$vtAu",
            "22HMbw$cHgGhRdemP6f2C6",
            "211C3db0rCG8l4C_u7bhhL",
            "13dER37tMjHB4$Ph9Xnpgk",
            "1YQlShCizeGOIu8A$364GO",
            "3xzSyYN3ZHJ8gCfY7dROFq",
            "3u8y5YPrgaJOtrPKZydY4a",
            "1S5CV3UIY5JB4Jfx_BV4eI",
            "3QuV_MrGzYIPolAWx8onn2",
            "0WrbHtN23RGvqjRihXM_7_",
            "2IThyL2s5ZIRxkJaQz$f3U",
            "0p5kr670uYJQOTg0_SN6rz",
            "3YK$QKpt42IuMHXT3WQVJ0",
            "2eaOKso5H6HelEc5kZy37U",
            "2Oh6T66W9IHAl2ZvepPCsx",
            "3_Gx0oTPclH8nfBbPmIEQ4",
            "23yAO$ysxJJvwmdd9ZeLiT",
            "2vpPAyMyyzGfRYBo3QUtcN",
            "0d8aeKJ$eWIvvDz9tSoiEZ",
            "3fAmpnmoxnIx7b8XEcfq6j",
            "3vM$dPkuYIHe$eMqnmwi$7",
            "1$E5tNSY5LHA6ow6ETx3LC",
            "3_X5MZ978VJPVV7LwD2ugo",
            "2sm9qOmjSAJvBqHos7tiPn",
            "38OqkKMKO2GAVLuXYSyKbe",
            "2IpRCS7NrUHxdnM$dghWml",
            "06KAnkIm4OJREjiX00bR2h",
            "3npsjT6gL8GACrxOx7wNM_",
            "01nTHwZS0THw0hU4ye1pGS",
            "1lRGFaaIU0JghjB_zudtLQ",
            "0HnBR$32zwJwV_JE$Y8_KL",
            "0KrlSDUQdbIwagJM80mwux",
            "2x$i7b627UI9d2Mz0CVkK_",
            "32dzHCkBA6Ie4HIw6jB6NV",
            "1d2cmSupHJGAr$8HNyxZGk",
            "3MZVpuY0z$GA2fNhylNg8A",
            "3DsaZLDGJSHQ3sZNEn1lkf"
        ],
        "neighbor": {
            "0.0": {
                "13": -5.4375,
                "3": 4.425000000000001
            },
            "3.7": {
                "13": -5.4375,
                "3": 4.425000000000001
            },
            "7.4": {
                "13": -5.4375,
                "3": 4.425000000000001
            },
            "11.1": {
                "13": -5.4375,
                "3": 4.425000000000001
            },
            "14.8": {
                "13": -5.4375,
                "3": 4.425000000000001
            }
        }
    },
    "3": {
        "type": "st",
        "storey": [
            0.0,
            3.7,
            7.4,
            11.1,
            14.8
        ],
        "location": [
            [
                9.8625,
                -68.0
            ],
            [
                9.8625,
                5.0894
            ]
        ],
        "ids": [
            "0NSeh1BI09Igi4vbyuaKeF",
            "0WG1mPGNt5IeaNzzx2WAw5",
            "0cHTWmzgFnIeLUqVaRU2r5",
            "0ec4au7QntG9OdPnilfQaT",
            "0g85o3stF9JOlEqmHUPGDD",
            "0kk6BaCK9nHwPjRn7KTTG5",
            "0kzqGAUCWVGfpGi$$2NWNW",
            "0wBFEdZ7TBHAWI0k6ZNCTO",
            "15Mbam17eJI8do7vEyF1y0",
            "16ypWvsDkyI8dYeCy92pQL",
            "1EwOwqn0waJeJWWOCvElkS",
            "1J7S573p1gIRpPmBQ9DLao",
            "1ZJtR2V3HEHAu2JptY8boJ",
            "1bIMP1DT_3GRuW6Ca94BH2",
            "1c$vSvSuTPJgY90ZkE10lo",
            "1gzhcA$hFVGBjSdDML3rP0",
            "1k1WEe9vArI9mIJ1wemnrA",
            "1scPI$$hB5GxoH23nZnkxH",
            "1ydTAn7UVcJehr2BkNs8p0",
            "20v6bL_D3HJ9lRzKIx40jF",
            "2HK5zyi2L5GwQA27yZuSu3",
            "2JlZSVwvcUGv2kOSwDA8cb",
            "2LQJBRih3vHQ6Qtt1rQaIQ",
            "2LpNbzKfzHI8DobtAMGW6c",
            "2PeSK7ouNoJ8q1swIAxZYq",
            "2ROQ8f8fKbIgY9QjFdTiNj",
            "2eQ3lWWAkZJetePkI71OND",
            "2eUy6SFUr1J9tROuUt8mYe",
            "2egdnCyMxoIPl2QOhTv5KY",
            "2sMIoazudMHQxkyQg5eYVt",
            "32AMfZi8L2HgvYbSndxy7_",
            "35ZE9Psd1KJhxNztVYRJfS",
            "36pbfZyaDGHvCVrlplvj73",
            "393bR9Iza4IeZqnsrYMM5O",
            "3AwmFTsuJCGvfF_8tKz_I_",
            "3BJTnRDl$JHxhagcXoM3kP",
            "3HZzjTwofFIh9pGqE3axdb",
            "3JAGpSM5qaHhJP9dk$RThI",
            "3ORmS4bZKuJfxwPirW_QMH",
            "3PN7HGN5L_H9jZZC4gttE6",
            "3QMnRkcJlxGfzrDHnGMlDR",
            "3V2LD0$pIQGOVbW_Ikx6MB",
            "3fdZzDj1RTIQqm6jB_bJWw",
            "3mNn0CExgjGBokV6XhHidT",
            "3xjfm2GYqDHwA_nNV12xFC",
            "3ykYS$uHCZGv1LFYMh3ikf",
            "3z3h3Khd4pJxOr$MmBGm34",
            "1x0XFakKzzIxU3MgxxNXJ0",
            "39069tzpr6IfXosV2UhmgM",
            "2vdT919GycIvxiJ0gJduKe",
            "3rwVmkwGMFH885EZsqWRAt",
            "0BM7rNI6BkIQvpmHmEUZXm",
            "3ngE2LW$6tIxFQUQ68s3h0",
            "0PQUjTZJ77H8c2o65SRf_j",
            "3WvgfejL7pHgDIfba2ExEa",
            "2B_ilMQGaDHhuzMBUhc2Xm",
            "3n_XZhL0abGh8sxfVgJwTJ",
            "3G_yjyvJfHIveQJDA$3W6O",
            "1OQOFLrpGQIgdbJXxxSfKg",
            "0uKkrE7ED7Je4vOqvaQrMr",
            "3oevGqT_$II9R_JTSgDDII",
            "2uvO90u4lfHhvKuyCOMd6K",
            "0oqMrg96mmHu6Si_yVyiJt",
            "2$4nTAOi8xJhhfEL5NS7OQ",
            "1RNLG22iBJIht0fRmp$BpS",
            "088LdODJxuIuFf7lfht$2f",
            "3fztzdIlPpHg83kzKS_485",
            "086R25gIxfHBjsw8y03rr1",
            "1ERyOD8m4QIAeOSJbyQPXS",
            "0LsYT0cECiIAoN5PNzxKoF",
            "0EtZQL1cPNHP$o$Osw1jjq",
            "1R3tt9O27YGh_n4tGYJu$S",
            "02Ayf8EjRuHAhx0_KOR0te",
            "2Ke$4HGVUYJ8sktu_y92zs",
            "3EKVJZ8HBhG8$HfXD_A0o$",
            "3p9xWrm04UH8aWyhQ2vavR",
            "0LLrLhUHmTHxSItpHyVKyn",
            "26k7kKNlOWJOgPgd5UpGQJ",
            "2hiJ8qIO15GuYuhzqvJPp3",
            "14sICHzKZoJe5S14VbFPd_",
            "2Efh9kRHcvJgRhxF0Ko35i",
            "0ofPPR3Zo8JBsCdpUr6SY2",
            "2VcaLXVXsZIv0MyjAOdeqX",
            "1nk2oDTxDBJAoTrR6M6a83",
            "2kkPjDGg3VJ8P57MhP$zpI",
            "3QUcE9g6VAHQDWzW_6R2No",
            "3eRgDSPSafIfKY4vUubDgB",
            "1OpBrRhhrWHhLJN_4_dDak",
            "3Ni31zBFU8HhCjEf3heL9Y",
            "1VjvVdtvV4I8un2Ao_DMho",
            "1KJUf3CjKfGRtL9XAGaB0m",
            "2tLUnAGLXiJhcThslta9YC",
            "1MMsUDcCpiHP7D$dBaf75A",
            "2FREn4Xk3QGBejnc$8h2Df",
            "2ziNgjTicyIQ0MqtxYJfYW",
            "07wDJ1Z$s2JPAwJPNIYYmd",
            "1wErsLt3jQIOnFKJOuQlhy",
            "3zNXwTq113GA8e5pyNvmLd",
            "0$4gEnTx8xIwiFffrTPUDJ",
            "1eFYAKpyatGwTSNlUJ1g4D",
            "0B2ZNT76w0HgXOblkQyn95",
            "3OXsBmwAbzIAGe_pJFTjx9",
            "0_BiDpQAVSHPe3gGWdP6KU"
        ],
        "neighbor": {
            "0.0": {
                "2": -4.425000000000001,
                "10": 5.4375
            },
            "3.7": {
                "2": -4.425000000000001,
                "10": 5.4375
            },
            "7.4": {
                "2": -4.425000000000001,
                "10": 5.4375
            },
            "11.1": {
                "2": -4.425000000000001,
                "10": 5.4375
            },
            "14.8": {
                "2": -4.425000000000001,
                "10": 5.4375
            }
        }
    },
    "4": {
        "type": "st",
        "storey": [
            0.0,
            3.7,
            7.4,
            11.1,
            14.8
        ],
        "location": [
            [
                -5.0,
                -57.5625
            ],
            [
                64.0632,
                -57.5625
            ]
        ],
        "ids": [
            "08tR_IcaesG9j_mBUNPdQ8",
            "0Cfz9cnnW8GhXqSBMFw_uo",
            "0FCNqdlJb1JRe8nEdGghs0",
            "0PQtTKjlJoIuRKIR96Vopy",
            "0WG1mPGNt5IeaNzzx2WAw5",
            "0Yv9XnTkZtJuXeiS6Dq1g5",
            "0_IjeNt$O5GAcqh1y7GW7z",
            "0mx$sstt_dJfMKuSii54yi",
            "0uohCJbu1FHAt17rWTxVlI",
            "0viRfa46HhH9CEBI8OzoNE",
            "1DRnOXjXp9HOPU7MjmuiGC",
            "1EwOwqn0waJeJWWOCvElkS",
            "1HeQj9Cxd7GQ44GRi8xfif",
            "1HtMuz9giQH8cZPrcwuE8m",
            "1iqYUYWIgZJAlBi$EulsNz",
            "1m5VdSLvyUGwSVP47WmUak",
            "1qdSkVCxrVGhez8DV4t8dZ",
            "1ssyW8VbBZGBA4crw$jv7A",
            "1xFvMsOpFLHO9HE2hchIRK",
            "22U4b2xZrAJg20B5d2hGxf",
            "28UwhyxhCdHA4jQWYdGSTy",
            "29qKHkPBOvHx5po5cwf0ZV",
            "2IyowlW7KCIghixJmuYdFz",
            "2LQJBRih3vHQ6Qtt1rQaIQ",
            "2YFQTJ6QrAHO5kpw37jjJR",
            "2bgZL618zXJvdh2t5$aive",
            "2jB$vm0LwFHvdy4tpyhdQH",
            "2opiX_9Hn0J8upKz7hZTFk",
            "2vuaT440YXIgTd5AgPW2Ob",
            "2xn$VLT0kcGgRKjymrOdgP",
            "30tbZDGe1KHuEUfwrKiknv",
            "36YQUUZ62PHwGx85Uis4l_",
            "36pbfZyaDGHvCVrlplvj73",
            "3HZzjTwofFIh9pGqE3axdb",
            "3Hus3wyLbPHvy1DL3LJUg7",
            "3KGjh_pxImIxkCXjKNUTEf",
            "3XCVdUkeD_Ie9_fbySrI1o",
            "3kOYTINoBoGRILn_w$9wkT",
            "3lT68n0ivaHhKn5s9UYBww",
            "3rGKjNu1wEJR3t2y38Xwkc",
            "3sehJ2rR1iHe6mxjBOf6Ej",
            "3zSEoz5S3TIPhS8pxxPuXi",
            "0WO4XqLN9WGuKUrXYhircV",
            "2bcezXdqRKIQvP2ikxc5YE",
            "1pjIpQTLsCHPNEaVySrhTW",
            "3zf8$bauYVHvbqyuVfYESo",
            "3v_WW26$pOGe6MfaMNrqUl",
            "1Qn63ip0ZbHQjZqpyzA9vP",
            "1QpDw5OBz7GfhdhDiUqui0",
            "2T_tSWMAcbHwCbamU0Okra",
            "3uZVyTkgW0GwDZXOThkjaw",
            "0iltTd1yinGP5t6cJ7zq11",
            "0h0RgtAy0DJBRYj5RR9N_H",
            "2OH0ru6I4IJxowKbv9fbGC",
            "3mu7mvI5VIHeqLwonTG7UH",
            "3RTs$yBWPzGOJR3Viq5_TR",
            "1Xz30RlCohIucCYTBC0wwP",
            "1ymxwnCZW0JuVZEzpj7RDn",
            "1VgWiEl_PyJhEznG5L3G$W",
            "2lEK1OjFuEIu3c4p8I037b",
            "3HfX6kwd_KIx0Znoy8tG8L",
            "2ScoMZNsp4J8jrcGUG4A_n",
            "0_jlzIgwh9JO4RjMoLl8Yl",
            "1I0e4LVgZeJv2m91AMetkj",
            "1s2i3IhL2oIRe3Ri3xkFs_",
            "3wh0BglvSQIwRvNMFVlqc$",
            "0hDmX4yWyOIAkYpIXDNGr0",
            "3xSFAaoHHEGACfeKtLXOB5",
            "2JYSFatVa1H8RSzWFgUWXX",
            "0Wj72l2ST4JhVBwTmS1kw0",
            "0nMWgJYFxFJBoY$knq$_eE",
            "2dvVX3WxmzHAH6d5xeKUgI",
            "2y0ZLCX3K4I9u08bUBv9Dv",
            "0KUpghINUGGv_Bj801TofM",
            "25OV2iicaRJ8Bh7MTwREd$",
            "397QVvplkhJwiuF7JuE9YM",
            "0cVb1WX26kIe$ZfTC0tIxx",
            "11kr98cWEeGgp0nG1hizEH",
            "0LMV5ESfb4HPesKIXouVtJ",
            "0z7XmAObE4Jvti_FDUAwgp",
            "1W5CxNPRtbHxZGqqYBOlFm",
            "2_txaLT_3sIgsRW15kmn1X"
        ],
        "neighbor": {
            "0.0": {
                "5": -4.424999999999997,
                "20": 5.437499999999993
            },
            "3.7": {
                "5": -4.424999999999997,
                "20": 5.437499999999993
            },
            "7.4": {
                "5": -4.424999999999997,
                "20": 5.437499999999993
            },
            "11.1": {
                "5": -4.424999999999997,
                "20": 5.437499999999993
            },
            "14.8": {
                "5": -4.424999999999997,
                "20": 5.437499999999993
            }
        }
    },
    "5": {
        "type": "st",
        "storey": [
            0.0,
            3.7,
            7.4,
            11.1,
            14.8
        ],
        "location": [
            [
                -5.0,
                -53.1375
            ],
            [
                64.0632,
                -53.1375
            ]
        ],
        "ids": [
            "04lqsQfwPXJvuVfb2ZXyue",
            "0BBQ1$QU$LIPfDOPGWry7i",
            "0HAt$lXehIHwN0SvWm0ngE",
            "0VGlCokFK5I9n_1G8k9bXZ",
            "0ePj2TUVD7IueZqEO7JRFZ",
            "0ec4au7QntG9OdPnilfQaT",
            "0f2W2hu0D0JPKvNgvmsAAs",
            "0kwReT7mBIIBxjR02SF6$J",
            "12QUdpX_5_I9Cl8yf_jHnp",
            "15Mbam17eJI8do7vEyF1y0",
            "16ypWvsDkyI8dYeCy92pQL",
            "19y2l68GH2IegH7s5kRwAz",
            "1FAooMA_lmJvYi_QXZkzbc",
            "1OdGGtsj6UJf$eoVXHLACb",
            "1Ol7DMjhmBIO7KrqOPg3s3",
            "1Zue55TWE6H8v7R$G7hhM6",
            "1i_W3z2PGhJOFUeo$k1yTa",
            "1n3USuNYNZHQJrfM7KfNqd",
            "1uwPQNXRFOHer0ZwL4$qt8",
            "25DmRaqFSrIvy1Mnv08SRL",
            "2ADDTsidlHIRj_TBMQcOic",
            "2HUTlQ1jQaJRGd8WvEr3nd",
            "2LSY2gGQ40Jf6Nfogc_V1w",
            "2dHT7L8W5aGgOGdXPi9g0r",
            "2eQ3lWWAkZJetePkI71OND",
            "2ob7N6xhqzIvceyEiIUeaX",
            "2rWXxK2vx0HAuLMyj6EpsA",
            "2yLJWe3tJ1GQGDI9rRbYSr",
            "34WoTTb5YpJ9OsW0L1QcK_",
            "36UGzvB2ZyIO1$XYjXFMU_",
            "3DIEuvc5EZHPxvwLO6GxP$",
            "3Hk96F0dsrGeigibaDs0O2",
            "3K4Irq37m3H8GE1g2b4fvM",
            "3aekocX9$YJ9tFpzu_yixl",
            "3boDl9ALyNHhkLlfKugSb3",
            "3hA8eXxaxqGvxIXUEgg7Qs",
            "3kEF20n0AJIgNOr3PwMhfw",
            "3kvH7WcBAnGhNgEbJsH1Dy",
            "3oVFMUdbwqHQreiIyN9bOU",
            "3paTauFHLbHh5oJk3xwcEj",
            "3yI2tURKrXIBJAHTuZW2B1",
            "3ykYS$uHCZGv1LFYMh3ikf",
            "2SgxHO9HZUGPKTYn_QDsvw",
            "0aHtCDosU2G9AP4kTGonDn",
            "0fdzAAO8yZG9sSaA7zIuqw",
            "2cmqB3CUUII88EDyD_7FZi",
            "3wKNFVOLcCJOLE_5Sf_HTK",
            "2X$KxsnwmRJxFTHvQYwPCe",
            "0FGWD6$IwpIOaQzhQpHDL5",
            "17sYzRHFFhIgvr6LzoZkpX",
            "1Kir2kLEPMHOvEm5dQh8if",
            "3LCNmQy27IJBAZLV2bl3ud",
            "3UUPxal80QJBu9NHkrRI_w",
            "3_jdPIpQswGPurhAetn8xl",
            "3IYRiNHKB7GwQx3437FF21",
            "1sfKr7LoyhIfpVz8rHsDFR",
            "19NdEpxXxnGvSK6la5MZ97",
            "1xCaVpcPFZJRa8B8cZTwuW",
            "1DvlnJxSRCJQHp22sYZ7A1",
            "0TxXaq$dziGBnUX12HLdQz",
            "0wSt56_WuWIAXDWi$spg6P",
            "2A6lH96BKYHxwtSsUgbuJN",
            "3Rmx_sC6UJGu_6U8CP9Q8D",
            "1qN9mVzlYiGuvWoNrDrzng",
            "3_qe_1hIkAJQcOux93xpXc",
            "32P6CDqQmbHPfaJm_jF6ew"
        ],
        "neighbor": {
            "0.0": {
                "18": -5.4375,
                "4": 4.424999999999997
            },
            "3.7": {
                "18": -5.4375,
                "4": 4.424999999999997
            },
            "7.4": {
                "18": -5.4375,
                "4": 4.424999999999997
            },
            "11.1": {
                "18": -5.4375,
                "4": 4.424999999999997
            },
            "14.8": {
                "18": -5.4375,
                "4": 4.424999999999997
            }
        }
    },
    "6": {
        "type": "st",
        "storey": [
            0.0,
            3.7,
            7.4,
            11.1,
            14.8
        ],
        "location": [
            [
                53.5625,
                -68.0
            ],
            [
                53.5625,
                5.0894
            ]
        ],
        "ids": [
            "0W_MK4RGSOJP_t0waZJwIA",
            "0pIeDBbIRnHBdb8jk1LPQP",
            "1HeQj9Cxd7GQ44GRi8xfif",
            "1Pz4H_iXzFGAE48JRCHYd1",
            "1uwPQNXRFOHer0ZwL4$qt8",
            "24oe56_9JcIRFMxdVJnq9J",
            "27B2pMdmxdGw7N_SMT0kb5",
            "28UwhyxhCdHA4jQWYdGSTy",
            "2GIl4r1FixIRhtri17Q6OY",
            "2ob7N6xhqzIvceyEiIUeaX",
            "2rWXxK2vx0HAuLMyj6EpsA",
            "2vuaT440YXIgTd5AgPW2Ob",
            "36YQUUZ62PHwGx85Uis4l_",
            "3AcFA7tGRRHxd2T93NGzNe",
            "3DIEuvc5EZHPxvwLO6GxP$",
            "3Hus3wyLbPHvy1DL3LJUg7",
            "3oVFMUdbwqHQreiIyN9bOU",
            "3yRpAqXyZvJgnPloJdlHkl",
            "3nXFpSBquvHeeQ$_rY6CQD",
            "1rHUNJvKuCGQbXtX1MWbOt",
            "01VuU2yOSdHvAeODgS1Xe_",
            "2$aCHyPdjMIQMRN41Xki9b",
            "2aMv2r9WbuGOrTYtt65$wT",
            "2Y3dNIvpjdJRNQ3o0RvuaI",
            "15jf8eaI8qGP1CxzK4L6q0",
            "3waPuLG65FJP$PeY_30QyX",
            "1oQuYyENCvIRDQ4A3emPzr",
            "2ImV0PrbCsG8vBoo7rAs3O",
            "2nKG8S4Dl7IRsHAqxBWCSq",
            "0LFKnPl2UqJg6B17lNQgqI",
            "3VVLI_jY5PIBuBC0UaMFuC",
            "2gEMFtBlXiHgMUnmj4ijYq",
            "0fH6pZpk0pIB1Wxk6bk4uV",
            "0IMzc3WFEdH9Rg$ujkOStG",
            "0l435lprdMG8OqJ8GMkf7l",
            "3aQS0dr4lkGRJeJ0tHDC3R",
            "0HcNPZLx3NJPncz2xni2h1",
            "3oF7Cm78utI8DEcmLAx64q",
            "3GfdN_LoxVIOZ4KRW3ErfE",
            "3M2A_rsSQPHRcn2xRh1efm",
            "0KoiayqsT5GRdsx21Ujd2_",
            "2tP8QUPeQ$GwMTxYeQhHuy",
            "3yWW7AD5MJJhHSaZJ$EJvh",
            "3r58W55dt4JfrxLXx3dqzB",
            "2K$rHLgXn6Hw3HvMCNQjLc",
            "0xZ6wkfYFMGfyzST4t_IxK"
        ],
        "neighbor": {
            "0.0": {
                "7": -4.42499999999999,
                "22": 5.4375
            },
            "3.7": {
                "7": -4.42499999999999,
                "22": 5.4375
            },
            "7.4": {
                "7": -4.42499999999999,
                "22": 5.4375
            },
            "11.1": {
                "7": -4.42499999999999,
                "22": 5.4375
            },
            "14.8": {
                "7": -4.42499999999999,
                "22": 5.4375
            }
        }
    },
    "7": {
        "type": "st",
        "storey": [
            0.0,
            3.7,
            7.4,
            11.1,
            14.8
        ],
        "location": [
            [
                49.1375,
                -68.0
            ],
            [
                49.1375,
                5.0894
            ]
        ],
        "ids": [
            "08wF6KXm5kGBr0OhAoDJy_",
            "0Cfz9cnnW8GhXqSBMFw_uo",
            "0mx$sstt_dJfMKuSii54yi",
            "105idiMOoLH9FDhTLBtDBy",
            "19y2l68GH2IegH7s5kRwAz",
            "1DRnOXjXp9HOPU7MjmuiGC",
            "1DzxpmnXSfGhJIjEBnAj5D",
            "1aYVFQvHAFIv0ItfiVTXOZ",
            "1i_W3z2PGhJOFUeo$k1yTa",
            "1n3USuNYNZHQJrfM7KfNqd",
            "22MVoErIIZJvSRElEkEk6e",
            "246X_wmoy$GBPSC43APCAJ",
            "25DmRaqFSrIvy1Mnv08SRL",
            "2Dnr5GjzcHGhOALb0xNGnk",
            "2YFQTJ6QrAHO5kpw37jjJR",
            "30tbZDGe1KHuEUfwrKiknv",
            "3TG00UresqJxRc2VeaOnx0",
            "3boDl9ALyNHhkLlfKugSb3",
            "0dMwBW$dSUGxMKmOeCBO8C",
            "3VUCmAj0xvHePS50Htp7Sr",
            "2vHfi3gQ0iGBYPZyocXhYQ",
            "0IZ$1br0UgGReaHkLepwFf",
            "1L$A57OR4SHhMd3cQZRA$x",
            "2E2edd6VtBIxgZndNjBuHp",
            "19daaF3KY9GPcM4eD$SE6f",
            "39mqElC934JOZEODsJXZVI",
            "397aAUBf8_GBIqi2YJ3zWa",
            "37axpdN7BvGeOvoodT6J9Q",
            "0jQlkcI72FJwYWBHNMHBHT",
            "2Pc4hbVcSJIOfKXAv0BvwG",
            "3YNDbhyLPwJuWlUV1mtesn",
            "0o2PQdNKlYGP0VrOzTPxCZ",
            "0pPnYWgwY$Ih6cwk3kZjlF",
            "2Z_SS3CwZDHhUc1VDqdmI5",
            "19Sy7Rh5oMJQenGw2XCao4",
            "35Q9EeOUYHIhjFtb2iTWE6",
            "3Q_EiGmfGoIvHvIp4M9_P$",
            "2RVk$tclZgHwuZKng8lV2B",
            "1enZdFnMASGxCBg3dZ$sZw",
            "3TqSodug9KJu4NCeU7mM$j",
            "1yld_uQS3CH9YLa6ntvhEo",
            "3w9c4QhDhrHB_Vz1K9qn6V",
            "3D4WtPhx9JGfHm0d8fOUK2",
            "0JsmYfYfv6Ig05bbXhpcgt",
            "3V9HucbqxBG8chkiY4sfTA",
            "2jP4TePkg3JwWBIWQ$Ow0m"
        ],
        "neighbor": {
            "0.0": {
                "11": -5.4375,
                "6": 4.42499999999999
            },
            "3.7": {
                "11": -5.4375,
                "6": 4.42499999999999
            },
            "7.4": {
                "11": -5.4375,
                "6": 4.42499999999999
            },
            "11.1": {
                "11": -5.4375,
                "6": 4.42499999999999
            },
            "14.8": {
                "11": -5.4375,
                "6": 4.42499999999999
            }
        }
    },
    "8": {
        "type": "st",
        "storey": [
            0.0,
            3.7,
            7.4,
            11.1,
            14.8
        ],
        "location": [
            [
                -5.0,
                -39.8625
            ],
            [
                64.0632,
                -39.8625
            ]
        ],
        "ids": [
            "08z9HKUu1nHgMKbRraK634",
            "0JTDpJ4GvAJAOAQtxyHb7L",
            "0L_P2jUa3xGgRUW9Ju4RcM",
            "0NSeh1BI09Igi4vbyuaKeF",
            "0wBFEdZ7TBHAWI0k6ZNCTO",
            "17$FrioAORJwKlxTF0SWfr",
            "1Ttu25Y1qAGgEe5VON4Ncd",
            "1k1WEe9vArI9mIJ1wemnrA",
            "1kBDQYd2joIgkUbtc_Miup",
            "1ydTAn7UVcJehr2BkNs8p0",
            "246X_wmoy$GBPSC43APCAJ",
            "27B2pMdmxdGw7N_SMT0kb5",
            "2IaxmBLl3SIQ0AgtaikTfH",
            "32AMfZi8L2HgvYbSndxy7_",
            "35cvsKgF7xGOU9pBuLYohO",
            "3JhJYWPfwcHReOyQwvBOqx",
            "3TJADEFfQuGOn64lCLEMIb",
            "3WvVKqx4RYGACs32gUsXQS",
            "3ZGRi0CAhgIOq8Vr14_zYu",
            "3j9ULnpZvqI9sfPiVCyM7j",
            "3mntQQF4KCH8fc9q_Qq7Fx",
            "3rEkJQWqvpHOh9T7lyy_Dw",
            "3uLqxSjeLaGQhhmLx3biDX",
            "1ab1$mMTaKIR$C6dtmdG7k",
            "3ZQ$2Zc_YxHPnn2Wp8tWt0",
            "3PRGZ$QjYCJx6h0yb8lTIE"
        ],
        "neighbor": {
            "0.0": {
                "17": -4.375,
                "1": 4.425000000000004
            },
            "3.7": {
                "17": -4.375,
                "1": 4.425000000000004
            },
            "7.4": {
                "17": -4.375,
                "1": 4.425000000000004
            },
            "11.1": {
                "17": -4.375,
                "1": 4.425000000000004
            },
            "14.8": {
                "17": -4.375,
                "1": 4.425000000000004
            }
        }
    },
    "9": {
        "type": "st",
        "storey": [
            0.0,
            3.7,
            7.4,
            11.1,
            14.8
        ],
        "location": [
            [
                27.2875,
                -68.0
            ],
            [
                27.2875,
                5.0894
            ]
        ],
        "ids": [
            "08tR_IcaesG9j_mBUNPdQ8",
            "0ePj2TUVD7IueZqEO7JRFZ",
            "0kwReT7mBIIBxjR02SF6$J",
            "0miYAJtW2bGu37shCi2A83",
            "0yHPX5HtO$Ju1RYmY0_3_r",
            "1FbcLkfh5DIg7WI3bXLJ2R",
            "1MlrihN1HXJxPWAwrAy4j1",
            "1PxhOghgl4IR$yhgeDaWZu",
            "1QL6VSKZwVIhFRZOYLs4_3",
            "1Zue55TWE6H8v7R$G7hhM6",
            "22U4b2xZrAJg20B5d2hGxf",
            "26HylFk1IVGBdr7Bnj3Luy",
            "2FAkntrisvI9DJ8lT2noo7",
            "2J12lxiukpG819fWIiNvqR",
            "2LSY2gGQ40Jf6Nfogc_V1w",
            "2jB$vm0LwFHvdy4tpyhdQH",
            "34WoTTb5YpJ9OsW0L1QcK_",
            "3KGjh_pxImIxkCXjKNUTEf",
            "3R41YqlcunIAu$ZPu_S1QB",
            "3bk_OmaWFMIBEiLpQvm_25",
            "3kOYTINoBoGRILn_w$9wkT",
            "3yqaTYJZyAHBC3EKq06hX3",
            "1Q6C$NcsKXJBSPSa7y5mzr",
            "1b$LSrVF29IRavRvu3ZwZd",
            "37eK3OGSEbHxYhsuMhxt9Q",
            "0JezhjeXGVJB2_45DGS92l"
        ],
        "neighbor": {
            "0.0": {
                "10": -11.9875,
                "21": 2.2124999999999986
            },
            "3.7": {
                "24": -4.425000000000001,
                "21": 2.2124999999999986
            },
            "7.4": {
                "24": -4.425000000000001,
                "21": 2.2124999999999986
            },
            "11.1": {
                "24": -4.425000000000001,
                "21": 2.2124999999999986
            },
            "14.8": {
                "24": -4.425000000000001,
                "21": 2.2124999999999986
            }
        }
    },
    "10": {
        "type": "st",
        "storey": [
            0.0,
            3.7,
            7.4,
            11.1,
            14.8
        ],
        "location": [
            [
                15.3,
                -68.0
            ],
            [
                15.3,
                5.0894
            ]
        ],
        "ids": [
            "3IZcXbxOQXHRYd2mpx4yiu",
            "3kY$ECpNqDIQVzGHOcGJGw",
            "3_DJ7YB_B2HA1DVdjXB71v",
            "2Kjpif4VnDHOWvABX2Q8CX",
            "1l32fycIZUJx5hi7er5Jwf",
            "14G6f3c_2FG98k0IlnQXuW",
            "0zewT8FmtVJxy7aS5LoQbc",
            "1JgBX4a_KHHhp8OIxN6jb7",
            "2ad35F6jIZJf_$IFl49ecj",
            "02M36E$LNQG8YAaRYVgJsI",
            "1DH8iOrTBwJe7dCHGrFsoj",
            "0P8B_0v10xIfj0Phl$$f0a",
            "2BL7b7FddeGgFBd1Jvl8Fd",
            "3GJOY1JmeuIwMc5Hc$NdcE",
            "1PdJL90TiaGeY3reKujcoZ",
            "20NJGsagXNJBVBALLSNpzz"
        ],
        "neighbor": {
            "0.0": {
                "3": -5.4375,
                "9": 11.9875
            },
            "3.7": {
                "3": -5.4375,
                "40": 3.1374999999999993
            },
            "7.4": {
                "3": -5.4375,
                "43": 3.1374999999999993
            },
            "11.1": {
                "3": -5.4375,
                "47": 3.1374999999999993
            },
            "14.8": {
                "3": -5.4375,
                "50": 3.1374999999999993
            }
        }
    },
    "11": {
        "type": "st",
        "storey": [
            0.0,
            3.7,
            7.4,
            11.1,
            14.8
        ],
        "location": [
            [
                43.7,
                -68.0
            ],
            [
                43.7,
                5.0894
            ]
        ],
        "ids": [
            "2tyAuf$rRoIf1SrDdLDody",
            "2Yh3hLb8cbJ9$iecmiREKd",
            "0FICUjJ5vuJfAaQsHZT0ex",
            "2oLOaqAdhPJhXN8PyFAYEy",
            "13q_ABFAMkGApM4jo0utYF",
            "3Y16uepn6KIO0tfMc9Jm2c",
            "3tFT2MNa5SIR_ZX_9SxJO$",
            "3RfyB4Elp$GR5HfDJ42Pqz",
            "0kyHFKAH3hHwEDkf5jdOHN",
            "0EodlQ6OFnIPDgNSuMSgKX"
        ],
        "neighbor": {
            "0.0": {
                "21": -14.20000000000001,
                "7": 5.4375
            },
            "3.7": {
                "27": -7.5625,
                "7": 5.4375
            },
            "7.4": {
                "27": -7.5625,
                "7": 5.4375
            },
            "11.1": {
                "27": -7.5625,
                "7": 5.4375
            },
            "14.8": {
                "27": -7.5625,
                "7": 5.4375
            }
        }
    },
    "12": {
        "type": "st",
        "storey": [
            0.0,
            3.7,
            7.4,
            11.1,
            14.8
        ],
        "location": [
            [
                15.0579,
                5.0894
            ],
            [
                64.0632,
                -60.251
            ]
        ],
        "ids": [
            "10LB_AwjBlIfgIuMdL3qRF",
            "3iY_SeDsl9HxF4wwpDPwrH",
            "0nOEuaRvt0GxT1HAaqSbux",
            "0e8Kt02WJ_Hggirl6VBPhE",
            "0kBNGOUFI0IeLek2j3yoQv",
            "03naA3mE4wH8BxVo9deVUe",
            "0ZRQOwYmULJBbqsYr8YHSL"
        ],
        "neighbor": {}
    },
    "13": {
        "type": "st",
        "storey": [
            0.0,
            3.7,
            7.4,
            11.1,
            14.8
        ],
        "location": [
            [
                -0.0,
                -68.0
            ],
            [
                -0.0,
                5.0894
            ]
        ],
        "ids": [
            "3oaeGxWj9MJRzYWrKWfc4o",
            "3TCfQbVKIfGhbq6$anutXp",
            "2APHwesfPVJPW51IaaHDbC",
            "0PCSdbh$AQJwH8$GLt1dbu",
            "3oanxa4bL5IuJQcbDkGziD",
            "0OtMGNNqY3GvzXVlMxBKd2"
        ],
        "neighbor": {
            "0.0": {
                "2": 5.4375
            },
            "3.7": {
                "2": 5.4375
            },
            "7.4": {
                "2": 5.4375
            },
            "11.1": {
                "2": 5.4375
            },
            "14.8": {
                "2": 5.4375
            }
        }
    },
    "14": {
        "type": "st",
        "storey": [
            0.0,
            3.7,
            7.4,
            11.1,
            14.8
        ],
        "location": [
            [
                34.1829,
                5.0894
            ],
            [
                64.0632,
                -34.751
            ]
        ],
        "ids": [
            "0I6Os1Cd7rJBH_vTp_8_iH",
            "2Wtd0Ji4sxJgwl$37EvHqR",
            "3RlZZJg_TzI9x4ik8$EObn",
            "2kapLgEszKGwuY2dO_ORPT",
            "1Vc_YYkv4eGgaXdkKkcDgW",
            "1oqOgOUwo_I93YpMs70IOM"
        ],
        "neighbor": {}
    },
    "15": {
        "type": "st",
        "storey": [
            0.0,
            3.7,
            7.4,
            11.1,
            14.8
        ],
        "location": [
            [
                -5.0,
                -31.5
            ],
            [
                64.0632,
                -31.5
            ]
        ],
        "ids": [
            "2rnnbyymWGHfhSB63coSTd",
            "3Bly6cZPCSHv8iNXghKPis",
            "2A37VM$L7PHuzP5JykNTNH",
            "1J0r6FwqE3JfmiSI9oOgdb",
            "0$vMyWLisXIBbkSMxp5PL6"
        ],
        "neighbor": {
            "0.0": {
                "16": -16.199999999999996,
                "17": 3.9875000000000007
            },
            "3.7": {
                "26": -8.362499999999997,
                "17": 3.9875000000000007
            },
            "7.4": {
                "26": -8.362499999999997,
                "17": 3.9875000000000007
            },
            "11.1": {
                "26": -8.362499999999997,
                "17": 3.9875000000000007
            },
            "14.8": {
                "26": -8.362499999999997,
                "17": 3.9875000000000007
            }
        }
    },
    "16": {
        "type": "st",
        "storey": [
            0.0,
            3.7,
            7.4,
            11.1,
            14.8
        ],
        "location": [
            [
                -5.0,
                -15.3
            ],
            [
                64.0632,
                -15.3
            ]
        ],
        "ids": [
            "2MD7cA5_A4JwIAm5BvIAG$",
            "1_ZWkBrU3OHRSnDB7AjP$e",
            "17q9PILOVfIxgl3Lkiaz58",
            "0qUnK3q6TXJxg7lO18PVsy",
            "1M8K0_m$_uJf5MTA5RY9Vo"
        ],
        "neighbor": {
            "0.0": {
                "19": -15.3,
                "15": 16.199999999999996
            },
            "3.7": {
                "41": -5.4375,
                "25": 3.412499999999998
            },
            "7.4": {
                "44": -5.4375,
                "25": 3.412499999999998
            },
            "11.1": {
                "46": -5.4375,
                "25": 3.412499999999998
            },
            "14.8": {
                "49": -5.4375,
                "25": 3.412499999999998
            }
        }
    },
    "17": {
        "type": "st",
        "storey": [
            0.0,
            3.7,
            7.4,
            11.1,
            14.8
        ],
        "location": [
            [
                -5.0,
                -35.4875
            ],
            [
                64.0632,
                -35.4875
            ]
        ],
        "ids": [
            "18EItECnEDJx_tqfTnKuY8",
            "2et3qWunYOI8wc4pqvPQaA",
            "0ddxALT6zxIe5fLWCkD0hc",
            "3e35mOxu4oGxfIjdhQONzC",
            "01SztCgR5rIx3j6fNU9nRc"
        ],
        "neighbor": {
            "0.0": {
                "15": -3.9875000000000007,
                "8": 4.375
            },
            "3.7": {
                "15": -3.9875000000000007,
                "8": 4.375
            },
            "7.4": {
                "15": -3.9875000000000007,
                "8": 4.375
            },
            "11.1": {
                "15": -3.9875000000000007,
                "8": 4.375
            },
            "14.8": {
                "15": -3.9875000000000007,
                "8": 4.375
            }
        }
    },
    "18": {
        "type": "st",
        "storey": [
            0.0,
            3.7,
            7.4,
            11.1,
            14.8
        ],
        "location": [
            [
                -5.0,
                -47.7
            ],
            [
                64.0632,
                -47.7
            ]
        ],
        "ids": [
            "0ZOLtKQyVHIu1rd_DTVDYs",
            "207sQ4KiHXJfLIYB3z3MyD",
            "1HliT7xi0dGRhUwt8X$It0",
            "1mFBhKbM$cGRyP8_BrXjnH",
            "1KAjwwhPMIJRQiLh9Gdb_y"
        ],
        "neighbor": {
            "0.0": {
                "1": -3.4125000000000014,
                "5": 5.4375
            },
            "3.7": {
                "1": -3.4125000000000014,
                "5": 5.4375
            },
            "7.4": {
                "1": -3.4125000000000014,
                "5": 5.4375
            },
            "11.1": {
                "1": -3.4125000000000014,
                "5": 5.4375
            },
            "14.8": {
                "1": -3.4125000000000014,
                "5": 5.4375
            }
        }
    },
    "19": {
        "type": "st",
        "storey": [
            0.0,
            3.7,
            7.4,
            11.1,
            14.8
        ],
        "location": [
            [
                -5.0,
                0.0
            ],
            [
                64.0632,
                0.0
            ]
        ],
        "ids": [
            "2L87$KGvS1G90hhPUm0KKl",
            "17$liwg3waGuD_YP$FF8vF",
            "3JPYnhEA6wIABHkLPqlRG9",
            "1LnapS7iFUIRFdFPerk3f1",
            "2YW2y9h71DHhtaHlbmrtTh"
        ],
        "neighbor": {
            "0.0": {
                "16": 15.3
            },
            "3.7": {
                "32": 5.4375
            },
            "7.4": {
                "34": 5.4375
            },
            "11.1": {
                "36": 5.4375
            },
            "14.8": {
                "38": 5.4375
            }
        }
    },
    "20": {
        "type": "st",
        "storey": [
            0.0,
            3.7,
            7.4,
            11.1,
            14.8
        ],
        "location": [
            [
                -5.0,
                -63.0
            ],
            [
                64.0632,
                -63.0
            ]
        ],
        "ids": [
            "0LeNZA__6FGRq1zB2cshUC",
            "2c0DrMFFGXGwhheByZhuEw",
            "0k$0jkyFx2IuPyPMcTgYQv",
            "0zQwN5D56CJg0$KXt56ng4",
            "1E_QA6$PgHIgpH$8Akqjbc"
        ],
        "neighbor": {
            "0.0": {
                "4": -5.437499999999993
            },
            "3.7": {
                "4": -5.437499999999993
            },
            "7.4": {
                "4": -5.437499999999993
            },
            "11.1": {
                "4": -5.437499999999993
            },
            "14.8": {
                "4": -5.437499999999993
            }
        }
    },
    "21": {
        "type": "st",
        "storey": [
            0.0,
            3.7,
            7.4,
            11.1,
            14.8
        ],
        "location": [
            [
                29.5,
                -68.0
            ],
            [
                29.5,
                5.0894
            ]
        ],
        "ids": [
            "0xbVIYLdSzJx74FWTx92Ls",
            "2P7ZULREiZGOaZ08yf863o",
            "3pCly0_C$uI9BJ1onvGMNf",
            "0IqxgQ5dSUIuS$XR0iFgd3",
            "2LjAHDJR87GOhziTWaILmj"
        ],
        "neighbor": {
            "0.0": {
                "9": -2.2124999999999986,
                "11": 14.20000000000001
            },
            "3.7": {
                "9": -2.2124999999999986,
                "27": 6.63750000000001
            },
            "7.4": {
                "9": -2.2124999999999986,
                "27": 6.63750000000001
            },
            "11.1": {
                "9": -2.2124999999999986,
                "27": 6.63750000000001
            },
            "14.8": {
                "9": -2.2124999999999986,
                "27": 6.63750000000001
            }
        }
    },
    "22": {
        "type": "st",
        "storey": [
            0.0,
            3.7,
            7.4,
            11.1,
            14.8
        ],
        "location": [
            [
                59.0,
                -68.0
            ],
            [
                59.0,
                5.0894
            ]
        ],
        "ids": [
            "22yK4M_uvIHwEAF$FmGG7l",
            "3IdGvpAzaPGuDfYKNp2OyT",
            "2HPuJBQaVsH8VJEchiIpu1",
            "2sh6zpqiv9I9mte7yjz52A",
            "3ghU6uWHfdJvNc6KyzxXTl"
        ],
        "neighbor": {
            "0.0": {
                "6": -5.4375
            },
            "3.7": {
                "6": -5.4375
            },
            "7.4": {
                "6": -5.4375
            },
            "11.1": {
                "6": -5.4375
            },
            "14.8": {
                "6": -5.4375
            }
        }
    },
    "23": {
        "type": "st",
        "storey": [
            0.0,
            3.7,
            7.4,
            11.1,
            14.8
        ],
        "location": [
            [
                -5.0,
                -54.2845
            ],
            [
                64.0632,
                -2.4822
            ]
        ],
        "ids": [
            "0r9RPf5NBWHB4dH7mVar9T",
            "2sEZIWEvUYIP2v6qcwBqRt",
            "1uWySd93UcHQqH0RyySLFU",
            "1AUSEbULR7HfVimEPbniO5",
            "27U6T$$7vnIfAqaaMlwq8Q"
        ],
        "neighbor": {}
    },
    "24": {
        "type": "st",
        "storey": [
            3.7,
            7.4,
            11.1,
            14.8
        ],
        "location": [
            [
                22.8625,
                -68.0
            ],
            [
                22.8625,
                5.0894
            ]
        ],
        "ids": [
            "1SWoC1DZT0HQp9_hePiIub",
            "2KIZ8ZBlVrJxoTxm5zlldt",
            "3eZJ9PGaGkJ8G9M4fMZK7Q",
            "0qVkkaCOOIH9XiURRawDCk",
            "111ThKMKLdIQ$uFCA1ygq$",
            "2ELk8KRCbqHhuS_JZrq9YY",
            "2ZkHbCeKQgHADEzqQcosTx",
            "2F5NcCIpbHJh03my45SENF"
        ],
        "neighbor": {
            "3.7": {
                "40": -4.425000000000001,
                "9": 4.425000000000001
            },
            "7.4": {
                "43": -4.425000000000001,
                "9": 4.425000000000001
            },
            "11.1": {
                "47": -4.425000000000001,
                "9": 4.425000000000001
            },
            "14.8": {
                "50": -4.425000000000001,
                "9": 4.425000000000001
            }
        }
    },
    "25": {
        "type": "st",
        "storey": [
            3.7,
            7.4,
            11.1,
            14.8
        ],
        "location": [
            [
                -5.0,
                -18.7125
            ],
            [
                64.0632,
                -18.7125
            ]
        ],
        "ids": [
            "1Y00V6wueKIxqn_Jn8d6IX",
            "3djJrQ1qF0IuaVt2hksOAs",
            "0f10RQ3elFGxoRkhIndCne",
            "1Vh2zT9tTZJgqRo4AvZAC_"
        ],
        "neighbor": {
            "3.7": {
                "16": -3.412499999999998,
                "26": 4.425000000000001
            },
            "7.4": {
                "16": -3.412499999999998,
                "26": 4.425000000000001
            },
            "11.1": {
                "16": -3.412499999999998,
                "26": 4.425000000000001
            },
            "14.8": {
                "16": -3.412499999999998,
                "26": 4.425000000000001
            }
        }
    },
    "26": {
        "type": "st",
        "storey": [
            3.7,
            7.4,
            11.1,
            14.8
        ],
        "location": [
            [
                -5.0,
                -23.1375
            ],
            [
                64.0632,
                -23.1375
            ]
        ],
        "ids": [
            "3uiLgHo0dGI87NyfRvimfH",
            "0nMaCX7uwqIea3cpWsO5Yq",
            "1hYAULbOOuGQrx1AHmP$xk",
            "0Nb1HWs7lpJucnqXeIg$VU"
        ],
        "neighbor": {
            "3.7": {
                "25": -4.425000000000001,
                "15": 8.362499999999997
            },
            "7.4": {
                "25": -4.425000000000001,
                "15": 8.362499999999997
            },
            "11.1": {
                "25": -4.425000000000001,
                "15": 8.362499999999997
            },
            "14.8": {
                "25": -4.425000000000001,
                "15": 8.362499999999997
            }
        }
    },
    "27": {
        "type": "st",
        "storey": [
            3.7,
            7.4,
            11.1,
            14.8
        ],
        "location": [
            [
                36.1375,
                -68.0
            ],
            [
                36.1375,
                5.0894
            ]
        ],
        "ids": [
            "1D3ISvp2gjIxFY3a3YeD$L",
            "1fk$0I5nvgJPk4sDHQEcUS",
            "1F1wisFI3KJ8ulvSsY_tZi",
            "0tbIFwF$7vI8JBzp$oQxww"
        ],
        "neighbor": {
            "3.7": {
                "21": -6.63750000000001,
                "11": 7.5625
            },
            "7.4": {
                "21": -6.63750000000001,
                "11": 7.5625
            },
            "11.1": {
                "21": -6.63750000000001,
                "11": 7.5625
            },
            "14.8": {
                "21": -6.63750000000001,
                "11": 7.5625
            }
        }
    },
    "28": {
        "type": "st",
        "storey": [
            3.7,
            7.4,
            11.1,
            14.8
        ],
        "location": [
            [
                -5.0,
                -59.6876
            ],
            [
                64.0632,
                -7.89
            ]
        ],
        "ids": [
            "0PNQGZmyHbGPmmXX248UAQ",
            "3xPTDqjgKmGQkYITBDX13d",
            "0WB4qH2EX2IRcHiftyfQK5",
            "1adHw8u7scHPooRqAa$suh"
        ],
        "neighbor": {}
    },
    "29": {
        "type": "st",
        "storey": [
            3.7,
            7.4,
            11.1,
            14.8
        ],
        "location": [
            [
                -5.0,
                -65.2188
            ],
            [
                64.0632,
                -13.4213
            ]
        ],
        "ids": [
            "0zdrBc509sG9dBTRNp_2_n",
            "2wkEbhysTfGfbNWpYUoNlu",
            "1z9ETuKpRbI8DLUfr3UOJV",
            "38NTqSiXrPGeRhu1AVLskv"
        ],
        "neighbor": {}
    },
    "30": {
        "type": "st",
        "storey": [
            3.7,
            7.4,
            11.1,
            14.8
        ],
        "location": [
            [
                -5.0,
                -43.094
            ],
            [
                59.2441,
                5.0894
            ]
        ],
        "ids": [
            "3KEXM1ObU3Gf6R2PQmcRax",
            "2bCClPA2MKJu_2f3UcsSpG",
            "15khpqApjQHwIIPbak_A9E",
            "19CmdOLVqwHBuR6vLfof4E"
        ],
        "neighbor": {}
    },
    "31": {
        "type": "st",
        "storey": [
            3.7,
            7.4,
            11.1,
            14.8
        ],
        "location": [
            [
                -5.0,
                -48.625
            ],
            [
                64.0632,
                3.1724
            ]
        ],
        "ids": [
            "16ZSZf3Z6qGvpcEm0NLuvn",
            "08KI$uHnbjIeFMBkdR9Yaa",
            "3nqyrFxwLKJ8CzvzLo7d8w",
            "2L1xa3$9moJPjQ6BoxvnwU"
        ],
        "neighbor": {}
    },
    "32": {
        "type": "ns",
        "storey": [
            3.7
        ],
        "location": [
            [
                -5.0,
                -5.4375
            ],
            [
                64.0632,
                -5.4375
            ]
        ],
        "ids": [
            "1Rz61D53LfIQCMwc6HH_2Y",
            "1TnSeAbO$tHBMU$sIVBgyR",
            "3ert2N5t8xH8raELB6LbXu",
            "1Eqw6_1GfBIR$pZh7XSjnL",
            "0b20q$JDnxGeNUeIn5iDqn",
            "1lK_LAGudQJuW4DqBvAofn"
        ],
        "neighbor": {
            "3.7": {
                "19": -5.4375,
                "41": 4.425000000000001
            }
        }
    },
    "33": {
        "type": "ns",
        "storey": [
            3.7
        ],
        "location": [
            [
                27.386,
                5.0894
            ],
            [
                64.0632,
                -43.8135
            ]
        ],
        "ids": [
            "2tA_ylWEvGGPGUv910pFOR",
            "2dXk4lUTtCHvs3GA$iwWKC",
            "3usP00NeD9JvKShECZ7pCJ",
            "3r$GxfDJoLHgeOONb1F2Jz",
            "2fFtYiMx4hIOzVoOWjFESl",
            "1riQYWt2_MIxqMd3QPWxPQ"
        ],
        "neighbor": {}
    },
    "34": {
        "type": "ns",
        "storey": [
            7.4
        ],
        "location": [
            [
                -5.0,
                -5.4375
            ],
            [
                64.0632,
                -5.4375
            ]
        ],
        "ids": [
            "1YcpagCtXHIh$orlr9hIcH",
            "3tEGYu2a5sGhvq3LVi_Aqt",
            "14X9dKZ6mJJBdX$YVF4FeV",
            "3uq75pBXYtIwjkXQjPnG2V",
            "3A_bF8S_5aIBk8T3woI0n_",
            "0axMHK9Pi0IxcqtIJ4QWMl"
        ],
        "neighbor": {
            "7.4": {
                "19": -5.4375,
                "44": 4.425000000000001
            }
        }
    },
    "35": {
        "type": "ns",
        "storey": [
            7.4
        ],
        "location": [
            [
                27.386,
                5.0894
            ],
            [
                64.0632,
                -43.8135
            ]
        ],
        "ids": [
            "08DpzL7DS6GOGQ7qKsaCwu",
            "2HMe_Q4XihJupKTcu3BKs3",
            "2RC3D_hXTFJP3m674cYHri",
            "2_5pUhZ1G0Jx$EqGWvHA__",
            "1Zi2R0PEm4GfDmoWKfJUdb",
            "0$fe9AqNxzJu2NQ1HHygWw"
        ],
        "neighbor": {}
    },
    "36": {
        "type": "ns",
        "storey": [
            11.1
        ],
        "location": [
            [
                -5.0,
                -5.4375
            ],
            [
                64.0632,
                -5.4375
            ]
        ],
        "ids": [
            "3sJegsHHM3HA9TsCcQHam4",
            "3OoKK0l4dMJwts4Gl5s58g",
            "0u$lgh3vzfGucYB6$FIiKC",
            "0Nq$$pcTHCJQkzCq0HiYou",
            "0txYtozv8QGeauavJ4WYFa",
            "3DSv1kx94wIOj7FCtH_IvJ"
        ],
        "neighbor": {
            "11.1": {
                "19": -5.4375,
                "46": 4.425000000000001
            }
        }
    },
    "37": {
        "type": "ns",
        "storey": [
            11.1
        ],
        "location": [
            [
                27.386,
                5.0894
            ],
            [
                64.0632,
                -43.8135
            ]
        ],
        "ids": [
            "2lyJ0b$QtTJhSCTeEYPJTG",
            "3rJIhL1vEKHQ7H7KtSCnBA",
            "0UguruK$gKIxp89sZ9IYQ4",
            "29oKnh9dJHHOMAnL6BpRqH",
            "3goIrSNoiFIvQqyyI08XHh",
            "00NVcS9$xZGv8t8ziVsy0p"
        ],
        "neighbor": {}
    },
    "38": {
        "type": "ns",
        "storey": [
            14.8
        ],
        "location": [
            [
                -5.0,
                -5.4375
            ],
            [
                64.0632,
                -5.4375
            ]
        ],
        "ids": [
            "2HWH_QD6xUJ8hcyMf3UZwC",
            "27ihRuR3BPHgU$XNzc2zJG",
            "24ajT1IZnXGelyLrmxd_hY",
            "1GcdtwxbPIJPh9gUoTQ7Md",
            "26SzvBtiRZJ9VMZn_y_X9J",
            "0hwJ12PQKWG8oGnbyeV2mU"
        ],
        "neighbor": {
            "14.8": {
                "19": -5.4375,
                "49": 4.425000000000001
            }
        }
    },
    "39": {
        "type": "ns",
        "storey": [
            14.8
        ],
        "location": [
            [
                27.386,
                5.0894
            ],
            [
                64.0632,
                -43.8135
            ]
        ],
        "ids": [
            "23Orj$ESmiJxfZx_uyLn6p",
            "2snT9GbtYZIgdgK3gc4KQ3",
            "0ZAT8N1CpKIOyqPzeteP6v",
            "22DhjJPOFRJBQ4LBnGhHMv",
            "2gcJbNJ2dFGg5qYgezL4LQ",
            "3kloVj$vGzIxkgQI_zvw_1"
        ],
        "neighbor": {}
    },
    "40": {
        "type": "ns",
        "storey": [
            3.7
        ],
        "location": [
            [
                18.4375,
                -68.0
            ],
            [
                18.4375,
                5.0894
            ]
        ],
        "ids": [
            "2l4mlyWm5pJPSE$VqDWZ08",
            "2g3bMB9pCtGwFAEGSd8gcA",
            "0zRTpjpuS_G88TNB7tAao$",
            "0Dd851otIgJg7T78eZ2_Gj"
        ],
        "neighbor": {
            "3.7": {
                "10": -3.1374999999999993,
                "24": 4.425000000000001
            }
        }
    },
    "41": {
        "type": "ns",
        "storey": [
            3.7
        ],
        "location": [
            [
                -5.0,
                -9.8625
            ],
            [
                64.0632,
                -9.8625
            ]
        ],
        "ids": [
            "3azYl7BaK1IvPATX$rKZF6",
            "2C4ibzDpCpI8prWUkeRjsL",
            "0KDn6WsTkpJfrNa8bZVvBH",
            "2qi1di_NADJAYECGqRspvA"
        ],
        "neighbor": {
            "3.7": {
                "32": -4.425000000000001,
                "16": 5.4375
            }
        }
    },
    "42": {
        "type": "ns",
        "storey": [
            3.7
        ],
        "location": [
            [
                21.8549,
                5.0894
            ],
            [
                64.0632,
                -51.1886
            ]
        ],
        "ids": [
            "0y_qbkLLXxJx4$NO4kF2VE",
            "2Bkn3DvICTHxa1au6dqnvV",
            "02uj9h49qPHeflRcZBsSEl",
            "2$JlXi1edRHQUIFNRLnfXO"
        ],
        "neighbor": {}
    },
    "43": {
        "type": "ns",
        "storey": [
            7.4
        ],
        "location": [
            [
                18.4375,
                -68.0
            ],
            [
                18.4375,
                5.0894
            ]
        ],
        "ids": [
            "1bnN5cjOLXHvQjGaOfunF2",
            "2URIFerUO4IQLDMjk77BS6",
            "1InLMK49g8GeAaQ9AdQQGQ",
            "3i6L8aU7txIRbvt7mvS7vg"
        ],
        "neighbor": {
            "7.4": {
                "10": -3.1374999999999993,
                "24": 4.425000000000001
            }
        }
    },
    "44": {
        "type": "ns",
        "storey": [
            7.4
        ],
        "location": [
            [
                -5.0,
                -9.8625
            ],
            [
                64.0632,
                -9.8625
            ]
        ],
        "ids": [
            "0f56ZyvteSGBdpXyWPvUe2",
            "2BYXcQR7D4Hw22FQi7DUoo",
            "1XtiRyjVpuJeB_aGZGHGhF",
            "2gYr8RSftsHu2LFxnlgY4f"
        ],
        "neighbor": {
            "7.4": {
                "34": -4.425000000000001,
                "16": 5.4375
            }
        }
    },
    "45": {
        "type": "ns",
        "storey": [
            7.4
        ],
        "location": [
            [
                21.8549,
                5.0894
            ],
            [
                64.0632,
                -51.1886
            ]
        ],
        "ids": [
            "0WQn$bXtR3JearK0BV7HoA",
            "3SrLV67wJqHwm2bh_bscKU",
            "2t8FVZH_KQGvUOPgl142RV",
            "1SzX7P7_tUJvKqvIJbjdpQ"
        ],
        "neighbor": {}
    },
    "46": {
        "type": "ns",
        "storey": [
            11.1
        ],
        "location": [
            [
                -5.0,
                -9.8625
            ],
            [
                64.0632,
                -9.8625
            ]
        ],
        "ids": [
            "1qAH_xQV1WHfN2JOwk29Vw",
            "1xWfQ4VX0RHPJu3C$Dwj11",
            "0OCYkVu1CkGOV1snVrxA30",
            "0eeVc0bOriJRNMycmHVbV3"
        ],
        "neighbor": {
            "11.1": {
                "36": -4.425000000000001,
                "16": 5.4375
            }
        }
    },
    "47": {
        "type": "ns",
        "storey": [
            11.1
        ],
        "location": [
            [
                18.4375,
                -68.0
            ],
            [
                18.4375,
                5.0894
            ]
        ],
        "ids": [
            "2RzeRo$fCeIwDc7B6$29gP",
            "1ahDezgG4JHQz3nKQygxq3",
            "2jQ0cEUjtqHAsaYkqeb22L",
            "11sce$43BqJPQsXt4YyJgj"
        ],
        "neighbor": {
            "11.1": {
                "10": -3.1374999999999993,
                "24": 4.425000000000001
            }
        }
    },
    "48": {
        "type": "ns",
        "storey": [
            11.1
        ],
        "location": [
            [
                21.8549,
                5.0894
            ],
            [
                64.0632,
                -51.1886
            ]
        ],
        "ids": [
            "1OPJFS0ru6GBPt3joEIttR",
            "0L2qqoDpXMIOOFjv$t4n6l",
            "1uoTMyriKkGgLxXkHXILLz",
            "2yJETyQ99tGglD1$UNniGm"
        ],
        "neighbor": {}
    },
    "49": {
        "type": "ns",
        "storey": [
            14.8
        ],
        "location": [
            [
                -5.0,
                -9.8625
            ],
            [
                64.0632,
                -9.8625
            ]
        ],
        "ids": [
            "2Tigpd7m9FGxJcchvzx91$",
            "28oG5mT6xhGx1foeK3YlR3",
            "2szDiTjGKYHPLjMAmblIx6",
            "3QO9tOL9wuGuDl$7daSl3b"
        ],
        "neighbor": {
            "14.8": {
                "38": -4.425000000000001,
                "16": 5.4375
            }
        }
    },
    "50": {
        "type": "ns",
        "storey": [
            14.8
        ],
        "location": [
            [
                18.4375,
                -68.0
            ],
            [
                18.4375,
                5.0894
            ]
        ],
        "ids": [
            "3LxwQu6NuFGvNfdlTeGefE",
            "0HW8vtA1FdJv4lU6$Yw_Yo",
            "3msQPkGBLmHQDwvv27ZXAg",
            "01v00D3UftHAjE1bBuZd5f"
        ],
        "neighbor": {
            "14.8": {
                "10": -3.1374999999999993,
                "24": 4.425000000000001
            }
        }
    },
    "51": {
        "type": "ns",
        "storey": [
            14.8
        ],
        "location": [
            [
                21.8549,
                5.0894
            ],
            [
                64.0632,
                -51.1886
            ]
        ],
        "ids": [
            "2JwTVrzQf1HfsWQzXdvG_h",
            "2tW_SynJRKHRNtkrAf4D7b",
            "0HoIturvHMJA6PM_2Y0jYl",
            "11bLqThthlHx8sayME6GhZ"
        ],
        "neighbor": {}
    }
}